{
  "CarName": "Honda NSX",
  "ToeFrontOffset": -0.4,
  "ToeRearOffset": -0.4,
  "ToeStep": 0.01,
  "BrakeTorqueOffset": 80,
  "BrakeBiasOffset": 50.0,
  "BrakeBiasStep": 0.2,
  "WheelRatesFront": [ 115000, 124000, 133000, 142000, 151000, 160000, 169000, 178000, 187000, 196000 ],
  "WheelRatesRear": [ 115000, 124000, 133000, 142000, 151000, 160000, 169000, 178000, 187000, 196000, 205000 ],
  "BumpStopRateOffset": 300,
  "BumpStopRateStep": 100,
  "CasterOffset": 8.8,
  "CasterStep": 0.1,
  "SteerRatioOffset": 10,
  "EcuOffset": 1,
  "PreloadOffset": 20,
  "PreloadStep": 10,
  "RideHeightFrontOffset": 54,
  "RideHeightRearOffset": 54,
  "CamberFrontOffset": -5.0,
  "CamberRearOffset": -5.0,
  "RearWingOffset": 0,
  "SplitterOffset": 0
}